matpy/__init__.py
matpy/log_util.py
matpy/matrixmultiplication.py
matpy/bins/__init__.py
matpy/bins/sample_bin.py
htmapp-0.0.4.dist-info/LICENSE
htmapp-0.0.4.dist-info/METADATA
htmapp-0.0.4.dist-info/WHEEL
htmapp-0.0.4.dist-info/entry_points.txt
htmapp-0.0.4.dist-info/top_level.txt
htmapp-0.0.4.dist-info/RECORD
