Metadata-Version: 2.1
Name: htmapp
Version: 0.0.4
Summary: How to make a Python package.
Home-page: https://github.com/lsawade/how_to_make_a_python_package
Author: Lucas Sawade, Peter Makus
Author-email: lsawade@princeton.edu
License: UNKNOWN
Project-URL: Documentation, https://how-to-make-a-python-package.readthedocs.io/en/latest/
Project-URL: TravisCI, https://travis-ci.com/github/lsawade/how_to_make_a_python_package
Keywords: Fun,Education,Learning,Programming
Platform: UNKNOWN
Classifier: Programming Language :: Python :: 3
Classifier: License :: OSI Approved :: GNU General Public License v3 or later (GPLv3+)
Classifier: Operating System :: OS Independent
Requires-Python: >=3.6
License-File: LICENSE
Requires-Dist: numpy
Provides-Extra: docs
Requires-Dist: sphinx ; extra == 'docs'
Requires-Dist: sphinx-rtd-theme ; extra == 'docs'
Provides-Extra: tests
Requires-Dist: pytest ; extra == 'tests'
Requires-Dist: py ; extra == 'tests'
